datasette_indieauth/__init__.py
datasette_indieauth/utils.py
datasette_indieauth/templates/indieauth.html
datasette_indieauth-1.2.2.dist-info/METADATA
datasette_indieauth-1.2.2.dist-info/WHEEL
datasette_indieauth-1.2.2.dist-info/entry_points.txt
datasette_indieauth-1.2.2.dist-info/top_level.txt
datasette_indieauth-1.2.2.dist-info/RECORD
