Metadata-Version: 2.1
Name: datasette-indieauth
Version: 1.2.2
Summary: Datasette authentication using IndieAuth and RelMeAuth
Home-page: https://github.com/simonw/datasette-indieauth
Author: Simon Willison
License: Apache License, Version 2.0
Project-URL: Issues, https://github.com/simonw/datasette-indieauth/issues
Project-URL: CI, https://github.com/simonw/datasette-indieauth/actions
Project-URL: Changelog, https://github.com/simonw/datasette-indieauth/releases
Requires-Python: >=3.7
Requires-Dist: datasette
Provides-Extra: test
Requires-Dist: pytest ; extra == 'test'
Requires-Dist: pytest-asyncio ; extra == 'test'
Requires-Dist: httpx ; extra == 'test'
Requires-Dist: pytest-httpx ; extra == 'test'
Requires-Dist: mf2py ; extra == 'test'
